LogELK/LogELK.py
LogELK/__init__.py
LogELK-1.0.4.dist-info/METADATA
LogELK-1.0.4.dist-info/WHEEL
LogELK-1.0.4.dist-info/top_level.txt
LogELK-1.0.4.dist-info/RECORD
