Metadata-Version: 2.1
Name: LogELK
Version: 1.0.4
Summary: Envia os logs para o ELK
Author: Jones Vieira
Author-email: <jones.vieira@tivit.com>
Requires-Dist: requests
